pythonFTP/FTPTools.py
pythonFTP/__init__.py
pythonFTP/ftplib2.py
pythonFTP-0.1.0.dist-info/.fuse_hidden0000114500000050
pythonFTP-0.1.0.dist-info/.fuse_hidden000011470000004f
pythonFTP-0.1.0.dist-info/.fuse_hidden0000114800000052
pythonFTP-0.1.0.dist-info/.fuse_hidden0000114900000051
pythonFTP-0.1.0.dist-info/LICENSE
pythonFTP-0.1.0.dist-info/METADATA
pythonFTP-0.1.0.dist-info/WHEEL
pythonFTP-0.1.0.dist-info/top_level.txt
pythonFTP-0.1.0.dist-info/RECORD
